<Properties StartupConfiguration="{65F6A84E-41F4-4CA0-8F04-DE44EB0CC081}|https">
  <MonoDevelop.Ide.Workbench ActiveDocument="SignalR_gRPC_Innovations/ServiceRegistration.cs">
    <Files>
      <File FileName="SignalR_gRPC_Innovations/ServiceRegistration.cs" Line="92" Column="42" />
      <File FileName="SignalR_gRPC_Innovations/WeatherForecast.cs" />
      <File FileName="SignalR_gRPC_Innovations/Controllers/WeatherForecastController.cs" Line="38" Column="2" />
      <File FileName="SignalR_gRPC_Innovations/Program.cs" Line="33" Column="3" />
      <File FileName="SignalR_gRPC_Innovations/Controllers/OutputCachingController.cs" Line="22" Column="32" />
    </Files>
    <Pads>
      <Pad Id="ProjectPad">
        <State name="__root__">
          <Node name="SignalR_gRPC_Innovations">
            <Node name="SignalR_gRPC_Innovations">
              <Node name="Controllers" expanded="True" />
              <Node name="Properties" expanded="True" />
              <Node name="ServiceRegistration.cs" selected="True" />
            </Node>
          </Node>
        </State>
      </Pad>
    </Pads>
  </MonoDevelop.Ide.Workbench>
  <MonoDevelop.Ide.DebuggingService.Breakpoints>
    <BreakpointStore />
  </MonoDevelop.Ide.DebuggingService.Breakpoints>
  <MonoDevelop.Ide.DebuggingService.PinnedWatches />
  <MonoDevelop.Ide.ItemProperties.SignalR__gRPC__Innovations PreferredExecutionTarget="/Applications/Google Chrome.app" />
  <MultiItemStartupConfigurations />
  <MonoDevelop.Ide.Workspace ActiveConfiguration="Debug" />
</Properties>